odoo/addons/barcode_action/README.rst
odoo/addons/barcode_action/__init__.py
odoo/addons/barcode_action/__manifest__.py
odoo/addons/barcode_action/demo/barcode_action_demo.xml
odoo/addons/barcode_action/i18n/barcode_action.pot
odoo/addons/barcode_action/i18n/es.po
odoo/addons/barcode_action/i18n/hr.po
odoo/addons/barcode_action/i18n/it.po
odoo/addons/barcode_action/i18n/pt.po
odoo/addons/barcode_action/i18n/zh_CN.po
odoo/addons/barcode_action/models/__init__.py
odoo/addons/barcode_action/models/res_partner.py
odoo/addons/barcode_action/readme/CONTRIBUTORS.md
odoo/addons/barcode_action/readme/DESCRIPTION.md
odoo/addons/barcode_action/readme/USAGE.md
odoo/addons/barcode_action/security/ir.model.access.csv
odoo/addons/barcode_action/static/description/icon.png
odoo/addons/barcode_action/static/description/index.html
odoo/addons/barcode_action/static/src/js/action_barcode_widget.esm.js
odoo/addons/barcode_action/tests/__init__.py
odoo/addons/barcode_action/tests/test_partner_find.py
odoo/addons/barcode_action/wizard/__init__.py
odoo/addons/barcode_action/wizard/barcode_action.py
odoo/addons/barcode_action/wizard/barcode_action_view.xml
odoo_addon_barcode_action-18.0.1.0.0.2.dist-info/METADATA
odoo_addon_barcode_action-18.0.1.0.0.2.dist-info/WHEEL
odoo_addon_barcode_action-18.0.1.0.0.2.dist-info/top_level.txt
odoo_addon_barcode_action-18.0.1.0.0.2.dist-info/RECORD
