Metadata-Version: 2.1
Name: odoo-addon-barcode_action
Version: 18.0.1.0.0.2
Requires-Python: >=3.10
Requires-Dist: odoo==18.0.*
Summary: Allows to use barcodes as a launcher
Home-page: https://github.com/OCA/server-ux
License: AGPL-3
Author: Creu Blanca, ForgeFlow, Odoo Community Association (OCA)
Author-email: support@odoo-community.org
Classifier: Programming Language :: Python
Classifier: Framework :: Odoo
Classifier: Framework :: Odoo :: 18.0
Classifier: License :: OSI Approved :: GNU Affero General Public License v3
